motu_datastore_client/__init__.py
motu_datastore_client/datastore_client.py
motu_datastore_client-0.1.1.dist-info/LICENSE
motu_datastore_client-0.1.1.dist-info/METADATA
motu_datastore_client-0.1.1.dist-info/WHEEL
motu_datastore_client-0.1.1.dist-info/top_level.txt
motu_datastore_client-0.1.1.dist-info/RECORD
