Metadata-Version: 2.1
Name: motu_datastore_client
Version: 0.1.1
Summary: A web client for interfacing with a MOTU AVB Server.
Author-email: Christopher Johnston <christopher_johnston@me.com>
License: MIT License
Project-URL: Homepage, https://github.com/ChristopherJohnston/motu_datastore_client
Keywords: motu,avb,client
Classifier: License :: OSI Approved :: MIT License
Classifier: Programming Language :: Python
Classifier: Programming Language :: Python :: 3
Requires-Python: >=3.11
License-File: LICENSE
Requires-Dist: aiohttp
